SolaScriptura-0.1.2.dist-info/DESCRIPTION.rst
SolaScriptura-0.1.2.dist-info/METADATA
SolaScriptura-0.1.2.dist-info/RECORD
SolaScriptura-0.1.2.dist-info/WHEEL
SolaScriptura-0.1.2.dist-info/entry_points.txt
SolaScriptura-0.1.2.dist-info/metadata.json
SolaScriptura-0.1.2.dist-info/top_level.txt
solascriptura/__init__.py
solascriptura/__main__.py
solascriptura/config.py
solascriptura/controller.py
solascriptura/gui_handler.py
solascriptura/library.py
solascriptura/messages.py
solascriptura/modules/__init__.py
