Metadata-Version: 2.0
Name: SolaScriptura
Version: 0.1.2
Summary: A cross-platform interactive Bible reader for the terminal
Home-page: https://github.com/glitchassassin/sola-scriptura
Author: Jon Winsley
Author-email: jon.winsley@gmail.com
License: MIT
Keywords: bible reader interactive terminal
Platform: UNKNOWN
Classifier: Development Status :: 4 - Beta
Classifier: Environment :: Console
Classifier: Intended Audience :: End Users/Desktop
Classifier: License :: OSI Approved :: MIT License
Classifier: Topic :: Religion
Requires-Dist: bs4
Requires-Dist: pysword
Requires-Dist: urwid
